{
  "Privacy Policy": [
    {
      "fetch": "https://www.tiktok.com/legal/privacy-policy?lang=en",
      "select": {
        "startBefore": "#privacy-eea",
        "endBefore": "#privacy-row"
      },
      "validUntil": "2021-07-15T15:06:00.000Z"
    }
  ],
  "In-App Purchases Policy": [
    {
      "fetch": "https://www.tiktok.com/legal/virtual-items?lang=en",
      "select": {
        "startBefore": "#virtual-items-eu",
        "endBefore": "#virtual-items-in"
      },
      "validUntil": "2022-06-16T06:41:14Z"
    },
    {
      "fetch": "https://www.tiktok.com/legal/virtual-items?lang=en",
      "select": [
        ".article-wrapper"
      ],
      "remove": [
        ".language-container",
        ".dropdown-title"
      ],
      "validUntil": "2022-12-22T00:43:03Z"
    }
  ],
  "Terms of Service": [
    {
      "fetch": "https://www.tiktok.com/legal/terms-of-use?lang=en",
      "select": {
        "startBefore": "#terms-eea",
        "endBefore": "#terms-in"
      },
      "validUntil": "2022-06-16T06:41:10Z"
    }
  ],
  "Law Enforcement Guidelines": [
    {
      "fetch": "https://www.tiktok.com/legal/law-enforcement?lang=en",
      "select": "article",
      "validUntil": "2022-12-22T00:42:57Z"
    }
  ]
}
